cip/__init__.py
cip/_core.py
cip/_internals.py
cip/dados/delta_pi_5M_a_10M.npy
cip_delta-0.2.0.dist-info/licenses/LICENSE.txt
cip_delta-0.2.0.dist-info/METADATA
cip_delta-0.2.0.dist-info/WHEEL
cip_delta-0.2.0.dist-info/top_level.txt
cip_delta-0.2.0.dist-info/RECORD
