Metadata-Version: 2.4
Name: cip-delta
Version: 0.2.0
Summary: Cifra de Integridade Primal
Author-email: Seu Nome <costaalv@alumni.usp.br>
License: MIT
Project-URL: Homepage, https://github.com/costaalv/projeto-delta
Requires-Python: >=3.8
License-File: LICENSE.txt
Requires-Dist: numpy
Requires-Dist: scipy
Dynamic: license-file
